cp_utils_hmv/__init__.py
cp_utils_hmv/data_reader.py
cp_utils_hmv/generic_functions.py
cp_utils_hmv/plot_utils.py
cp_utils_hmv-0.2.0.dist-info/LICENSE
cp_utils_hmv-0.2.0.dist-info/METADATA
cp_utils_hmv-0.2.0.dist-info/WHEEL
cp_utils_hmv-0.2.0.dist-info/top_level.txt
cp_utils_hmv-0.2.0.dist-info/RECORD
